lancet/__init__.py
lancet/base.py
lancet/cli.py
lancet/default-settings.ini
lancet/git.py
lancet/helper.sh
lancet/helpers.py
lancet/issue_tracker.py
lancet/keyring.py
lancet/scm_manager.py
lancet/settings.py
lancet/timer.py
lancet/utils.py
lancet/autocomplete/zsh.sh
lancet/commands/__init__.py
lancet/commands/configuration.py
lancet/commands/harvest.py
lancet/commands/issues.py
lancet/commands/repository.py
lancet/commands/services.py
lancet/commands/workflow.py
lancet/templates/contributors.rst
lancet/templates/pull-request.txt
lancet/templates/release-notes.md
lancet/test/__init__.py
lancet/test/helpers.py
lancet/test/requirements.txt
lancet/test/test_configuration.py
lancet/test/test_services.py
lancet-0.8.1.dist-info/LICENSE
lancet-0.8.1.dist-info/METADATA
lancet-0.8.1.dist-info/WHEEL
lancet-0.8.1.dist-info/entry_points.txt
lancet-0.8.1.dist-info/top_level.txt
lancet-0.8.1.dist-info/RECORD
