Metadata-Version: 2.1
Name: lancet
Version: 0.8.1
Summary: Command line utility used by Divio.
Home-page: https://github.com/divio/lancet
Author: Divio AG
Author-email: info@divio.ch
License: MIT
Platform: UNKNOWN
Classifier: Development Status :: 4 - Beta
Classifier: Environment :: Web Environment
Classifier: Intended Audience :: Developers
Classifier: License :: OSI Approved :: MIT License
Classifier: Operating System :: OS Independent
Classifier: Programming Language :: Python
Classifier: Programming Language :: Python :: 3
Classifier: Programming Language :: Python :: 3.4
Classifier: Programming Language :: Python :: 3.5
Classifier: Programming Language :: Python :: 3.6
Classifier: Programming Language :: Python :: 3.7
License-File: LICENSE
Requires-Dist: attrs
Requires-Dist: click
Requires-Dist: git-url-parse
Requires-Dist: github3.py
Requires-Dist: Jinja2
Requires-Dist: jira
Requires-Dist: keyring
Requires-Dist: keyrings.alt
Requires-Dist: pygit2
Requires-Dist: python-gitlab
Requires-Dist: python-slugify
Requires-Dist: requests
Requires-Dist: sentry-sdk
Requires-Dist: tabulate
Requires-Dist: uritemplate.py
